Workbook

Sheet Configuracion
A1: ID_Config | B1: Tasa_BCV_Bs_USD | C1: Ultima_Actualizacion | D1: Nombre_Negocio
A2: CFG-001 | B2: 860.18 | C2: 2026-10-01 | D2: Mi Abasto AppSheet POS

Sheet Productos
A1: ID_Producto | B1: Codigo_Barras | C1: Nombre_Producto | D1: Categoria | E1: Precio_USD | F1: Precio_Bs | G1: Stock_Actual | H1: Estado
A2: PROD-001 | B2: 7591001001011 | C2: BelVita Kraker con Afrecho 26g | D2: Galletas | E2: 0.5 | F2: =E2*Configuracion!$B$2 -> 430.09 | G2: 24 | H2: Disponible
A3: PROD-002 | B3: 7591001001028 | C3: Club Social Original 26g | D3: Galletas | E3: 0.6 | F3: =E3*Configuracion!$B$2 -> 516.108 | G3: 36 | H3: Disponible
A4: PROD-003 | B4: 7591001001035 | C4: BelVita Miel y Cereal 26g | D4: Galletas | E4: 0.55 | F4: =E4*Configuracion!$B$2 -> 473.099 | G4: 18 | H4: Disponible
A5: PROD-004 | B5: 7591002002018 | C5: Espagueti Mary 1kg | D5: Pasta | E5: 1.3 | F5: =E5*Configuracion!$B$2 -> 1118.234 | G5: 20 | H5: Disponible
A6: PROD-005 | B6: 7591002002025 | C6: Espagueti La Molina 1kg | D6: Pasta | E6: 1.25 | F6: =E6*Configuracion!$B$2 -> 1075.225 | G6: 20 | H6: Disponible
A7: PROD-006 | B7: 7591003003015 | C7: Arroz Blanco Premium La Molina 900g | D7: Granos/Arroz | E7: 1.1 | F7: =E7*Configuracion!$B$2 -> 946.198 | G7: 30 | H7: Disponible
A8: PROD-007 | B8: 7591003003022 | C8: Arroz Premium Santoni 900g | D8: Granos/Arroz | E8: 1.15 | F8: =E8*Configuracion!$B$2 -> 989.207 | G8: 25 | H8: Disponible
A9: PROD-008 | B9: 7591003003039 | C9: Arroz Monic Fuente de Energía 900g | D9: Granos/Arroz | E9: 1.05 | F9: =E9*Configuracion!$B$2 -> 903.189 | G9: 20 | H9: Disponible
A10: PROD-009 | B10: 7591003003046 | C10: Arroz Mary Superior 1kg | D10: Granos/Arroz | E10: 1.2 | F10: =E10*Configuracion!$B$2 -> 1032.216 | G10: 30 | H10: Disponible
A11: PROD-010 | B11: 7591004004012 | C11: Salsa de Ajo Iberia 165g | D11: Salsas | E11: 1.4 | F11: =E11*Configuracion!$B$2 -> 1204.252 | G11: 15 | H11: Disponible
A12: PROD-011 | B12: 7591004004029 | C12: Salsa Inglesa Coma 150ml | D12: Salsas | E12: 1.35 | F12: =E12*Configuracion!$B$2 -> 1161.243 | G12: 12 | H12: Disponible
A13: PROD-012 | B13: 7591004004036 | C13: Salsa de Soya Don Pedro 150ml | D13: Salsas | E13: 1.5 | F13: =E13*Configuracion!$B$2 -> 1290.27 | G13: 15 | H13: Disponible
... A25: PROD-024 | B25: 7591007007037 | C25: Whisky Black & White 0.75L | D25: Licores | E25: 12 | F25: =E25*Configuracion!$B$2 -> 10322.16 | G25: 4 | H25: Disponible

Sheet Clientes
A1: ID_Cliente | B1: Nombre_Cliente | C1: Telefono | D1: Total_Deuda_USD | E1: Total_Deuda_Bs | F1: Estado_Cuenta
A2: CLI-001 | B2: Pedro Pérez | C2: 0412-1234567 | D2: =SUMIF(Cuentas_Por_Cobrar!B:B,A2,Cuentas_Por_Cobrar!G:G) -> 5 | E2: =D2*Configuracion!$B$2 -> 4300.9 | F2: =IF(D2>0,"Con Deuda Pendiente","Solvente") -> Con Deuda Pendiente
A3: CLI-002 | B3: María Rodríguez | C3: 0414-7654321 | D3: =SUMIF(Cuentas_Por_Cobrar!B:B,A3,Cuentas_Por_Cobrar!G:G) -> 7.5 | E3: =D3*Configuracion!$B$2 -> 6451.35 | F3: =IF(D3>0,"Con Deuda Pendiente","Solvente") -> Con Deuda Pendiente
A4: CLI-003 | B4: José Gómez | C4: 0424-9876543 | D4: =SUMIF(Cuentas_Por_Cobrar!B:B,A4,Cuentas_Por_Cobrar!G:G) -> 0 | E4: =D4*Configuracion!$B$2 -> 0 | F4: =IF(D4>0,"Con Deuda Pendiente","Solvente") -> Solvente

Sheet Cuentas_Por_Cobrar
A1: ID_Fiado | B1: ID_Cliente | C1: Cliente_Nombre | D1: Fecha_Credito | E1: Monto_Original_USD | F1: Total_Abonado_USD | G1: Saldo_Pendiente_USD | H1: Saldo_Pendiente_Bs | I1: Estado_Fiado
A2: FIA-001 | B2: CLI-001 | C2: =VLOOKUP(B2,Clientes!A:B,2,FALSE) -> Pedro Pérez | D2: 2026-10-01 | E2: 10 | F2: =SUMIF(Abonos_Pagos!B:B,A2,Abonos_Pagos!E:E) -> 5 | G2: =E2-F2 -> 5 | H2: =G2*Configuracion!$B$2 -> 4300.9 | I2: =IF(G2<=0,"PAGADO",IF(F2>0,"ABONADO (MOROSO)","PENDIENTE TOTAL")) -> ABONADO (MOROSO)
A3: FIA-002 | B3: CLI-002 | C3: =VLOOKUP(B3,Clientes!A:B,2,FALSE) -> María Rodríguez | D3: 2026-10-01 | E3: 15 | F3: =SUMIF(Abonos_Pagos!B:B,A3,Abonos_Pagos!E:E) -> 7.5 | G3: =E3-F3 -> 7.5 | H3: =G3*Configuracion!$B$2 -> 6451.35 | I3: =IF(G3<=0,"PAGADO",IF(F3>0,"ABONADO (MOROSO)","PENDIENTE TOTAL")) -> ABONADO (MOROSO)

Sheet Abonos_Pagos
A1: ID_Abono | B1: ID_Fiado | C1: ID_Cliente | D1: Fecha_Abono | E1: Monto_Abonado_USD | F1: Tasa_BCV | G1: Monto_Abonado_Bs | H1: Metodo_Pago | I1: Notas_Abono
A2: ABO-001 | B2: FIA-001 | C2: CLI-001 | D2: 2026-10-01 | E2: 5 | F2: =Configuracion!$B$2 -> 860.18 | G2: =E2*F2 -> 4300.9 | H2: Pago Móvil | I2: Abonó el 50% de la cuenta. Queda debiendo $5.00
A3: ABO-002 | B3: FIA-002 | C3: CLI-002 | D3: 2026-10-01 | E3: 7.5 | F3: =Configuracion!$B$2 -> 860.18 | G3: =E3*F3 -> 6451.35 | H3: Efectivo USD | I3: Abonó la mitad de la cuenta.

Sheet Ventas
A1: ID_Venta | B1: Fecha_Hora | C1: ID_Cliente | D1: Tipo_Venta | E1: Total_USD | F1: Total_Bs | G1: Estado_Pago
A2: VEN-001 | B2: 2026-10-01 09:30:00 | C2: CLI-001 | D2: Fiado / Crédito | E2: 10 | F2: =E2*Configuracion!$B$2 -> 8601.8 | G2: Credito Registrado
A3: VEN-002 | B3: 2026-10-01 10:15:00 | C3: CLI-002 | D3: Fiado / Crédito | E3: 15 | F3: =E3*Configuracion!$B$2 -> 12902.7 | G3: Credito Registrado
A4: VEN-003 | B4: 2026-10-01 11:00:00 | C4: Publico General | D4: Contado | E4: 4.5 | F4: =E4*Configuracion!$B$2 -> 3870.81 | G4: PAGADO

Sheet Detalle_Ventas
A1: ID_Detalle | B1: ID_Venta | C1: Codigo_Barras | D1: ID_Producto | E1: Nombre_Producto | F1: Cantidad | G1: Precio_Unitario_USD | H1: Subtotal_USD | I1: Subtotal_Bs
A2: DET-001 | B2: VEN-001 | C2: 7591004004043 | D2: PROD-013 | E2: Salsa Bolognesa Cucina D'Italia | F2: 2 | G2: 2.2 | H2: =F2*G2 -> 4.4 | I2: =H2*Configuracion!$B$2 -> 3784.792
A3: DET-002 | B3: VEN-001 | C3: 7591006006023 | D3: PROD-020 | E3: Kellogg's Choco Zucaritas 300g | F3: 1 | G3: 3.9 | H3: =F3*G3 -> 3.9 | I3: =H3*Configuracion!$B$2 -> 3354.702
A4: DET-003 | B4: VEN-001 | C4: 7591003003022 | D4: PROD-007 | E4: Arroz Premium Santoni 900g | F4: 1 | G4: 1.7 | H4: =F4*G4 -> 1.7 | I4: =H4*Configuracion!$B$2 -> 1462.306
